[
  {
    "type": "meta",
    "title": "The Introduction",
    "subtitle": "",
    "language": "English",
    "date": "2026-04-08",
    "youtubeUrl": "https://youtu.be/FIuVqVjhnEo",
    "pdfUrl": "https://themillenniumpost.com/download/morning-light/pdf/2026-APR-EN/08-04-2026-EN.pdf",
    "imageUrl": "",
    "audioUrl": ""
  },
  {
    "type": "verse",
    "reference": "Numbers chapter 7",
    "text": ""
  },
  {
    "type": "paragraph",
    "content": "Today we come to Numbers chapter 7. After Yahweh gave laws about cleansing the camp, guarding holiness, and living in separation, He now shows something very practical: how the people of Israel supported the worship and service around the tabernacle. Numbers 7 is a long chapter, It is a record of love, order, and careful obedience. It shows how the leaders of the tribes honored Yahweh’s dwelling place and how they brought gifts in an organized way, according to Yahweh’s structure.\n\nNumbers 7 begins with the tabernacle being set up and dedicated.\nMoses anointed it and set it apart, along with the altar and all the vessels used for service. In that moment, the leaders of Israel; chief men of the tribes, came forward with offerings. These were not random gifts from emotion. They were planned offerings, brought in a holy order, connected to the work of the tabernacle and the needs of the Levites who carried and served. The chapter shows that when God’s presence is in the midst of His people, the people respond with worship and with practical support.\n\nOne of the first things Numbers 7 records is the bringing of wagons and oxen. The leaders brought these so the Levites could carry the heavy parts of the tabernacle during the journeys in the wilderness. Yahweh then told Moses how these wagons and oxen should be distributed. The Gershonites received wagons and oxen according to their service, and the Merarites received more because their loads were heavier. But the Kohathites received none, because their holy burden was carried on the shoulders. This teaches that Yahweh’s service is not only spiritual words; it also includes practical responsibility. Yahweh’s work had weight. The people had to move together. And Yahweh gave order, so that each group served in the way Yahweh appointed.\n\nAfter this, the chapter records the offerings brought by each tribe. For twelve days, the leaders came one by one, tribe by tribe, and each brought the same set of offerings. Each day is written in full detail. The same items are repeated again and again, with the name of each leader and the name of each tribe.\nYahweh could have written it once and said, “All the tribes brought the same.” But God chose to write every day, every name, and every gift. This shows that our God sees each offering personally. He remembers each act of devotion.\nHe does not forget the obedience of one tribe because another tribe did the same. In his record, each day matters, each leader matters, and each offering is noticed.\n\nThe offerings themselves include silver and gold items, grain offerings, burnt offerings, sin offerings, and peace offerings. This means the chapter is not only about generosity. It is about approaching the Almighty correctly. It reflects sacrifice, cleansing, dedication, and fellowship. Even though the gifts are the same, the chapter’s long listing creates a steady rhythm, like a procession of worship. It shows unity without competition. No tribe is made higher than another through larger gifts. Each gives the same, and God receives each one. That is a powerful lesson for the heart. God loves equality in devotion. He loves order in worship. He loves the whole camp moving together, not as scattered individuals, but as one people under His covenant.\n\nNear the end of Numbers 7, the chapter comes to a very holy closing line.\nIt says that when Moses entered the tabernacle, he heard the voice speaking to him from above the mercy seat, from between the cherubim. This reminds us that all the offerings and all the order were not empty religion. Yahweh was truly present. He truly spoke. He was guiding His people. The tabernacle was not only a tent. It was the center of Yahweh’s covenant presence and Yahweh’s communication with Israel.\n\nSo, Numbers 7 is a chapter about dedication, worship, order, support for Yahweh’s service, and the leaders of Israel bringing offerings before Yahweh in a careful, equal, and organized way. It looks repetitive, but it is full of meaning. There are many detailed truths hidden inside this chapter, and we will start studying them one by one."
  },
  {
    "type": "prayer",
    "title": "Prayer",
    "text": "Yahweh our Father, praise be to Your holy name.\nThank You for Your presence among Your people, and for the order You establish so worship is pure and pleasing.\nThank You for teaching us that every offering matters, every act of obedience is seen, and every name is remembered by You.\nBuild in us a willing heart to support what is holy, to serve without pride, and to worship without competition.\nGive us unity, sincerity, and faithfulness as we walk in the path You set before us.\nLet our lives be a living offering of gratitude, and let our hearts stay near to Your voice.\nWe pray in Christ’s holy name, amen."
  }
]