[
  {
    "type": "meta",
    "title": "Guard the Vow",
    "subtitle": "The Nazarite Vow – 9",
    "language": "English",
    "date": "2026-03-14",
    "youtubeUrl": "https://youtu.be/76zSM9g5xZ0",
    "pdfUrl": "https://themillenniumpost.com/download/morning-light/pdf/2026-MAR-EN/14-03-2026-EN.pdf",
    "imageUrl": "",
    "audioUrl": ""
  },
  {
    "type": "verse",
    "reference": "Numbers chapter 6:1-21",
    "text": ""
  },
  {
    "type": "paragraph",
    "content": "Continuing from where we stopped, Numbers 6 shows that Yahweh’s vow of separation was not only tested by what a Nazirite chose, but also by what could happen suddenly around the Nazirite. The passage says that if someone dies suddenly beside the Nazirite, the consecrated head becomes defiled. In that case, the Nazirite must wait seven days and then shave the head. On the eighth day, the Nazirite must bring two turtledoves or two young pigeons to the priest at the entrance of the tabernacle. The priest offers one bird as a sin offering and the other as a burnt offering. In that way, the Nazirite is purified from the guilt connected with contact with death. Then the person must begin the vow again. Yahweh is teaching that consecration is precious, but it must also be guarded, because defilement can interrupt what is holy.\n\nThis defilement is important to understand. It happens because of proximity to death, not because the hair physically touched the dead body. In the Law of Moses, death creates ritual uncleanness that spreads beyond direct touch. Numbers 19 gives a clear example: “This is the law when someone dies in a tent: everyone who comes into the tent and everything in the tent shall be unclean seven days” (Numbers 19:14). So uncleanness spreads simply by being in the same place, under the same covering, and in the immediate presence of death. That is why the Nazirite can be defiled even if the hair never touches the corpse. Death occurred beside him, and the holy status attached to his head is treated as contaminated. The text says, “his consecrated head is defiled,” not because the hair is magical, but because the vow resting upon the head has been interrupted by an unclean presence.\n\nWhy does death cause defilement in the first place? In Scripture, Yahweh is the living God, the source of life. Death entered through sin, and death stands as the opposite of holiness and life. So in the camp, death carried a defiling shadow. The Nazirite lived with a priest-like level of separation for that season, so Yahweh required distance from death. If death appeared close, even suddenly, the vow was disrupted and had to be reset through the cleansing steps Yahweh commanded.\n\nThis is where the New Covenant lesson becomes very clear for New Creation believers. We are also called to a life of consecration. Scripture tells us to present our bodies as a living sacrifice, holy and acceptable to Yahweh (Romans 12:1). It also calls us to be holy in all our conduct (1 Peter 1:15-16). Yahweh’s purpose is that we become like His Son, being conformed to the image of Christ\n(Romans 8:29). So the Nazirite’s interruption becomes a picture for us.\nWhen a corpse appears beside the Nazirite, spiritually it can represent sinful influences or fleshly works that appear close to our life. The Nazirite became defiled even without choosing it and even without touching. This teaches a principle: closeness to death affects consecration.\n\nThe New Testament teaches the same truth with plain words. “Bad company corrupts good character” (1 Corinthians 15:33). And again, “Have no fellowship with the unfruitful works of darkness” (Ephesians 5:11). Even if a believer does not actively participate in sin, constant closeness to it can weaken the conscience and dull the fear of Yahweh. When wrong speech, pride, bitterness, lust, and jealousy stay near; through friends, entertainment, workplace culture, or secret habits; consecration is quietly disturbed. The person may say, “I did not touch it,” yet the influence remained close, and the heart became affected.\n\nFor believers, Christ is the Head of the body (Colossians 1:18). Our life is meant to show His glory. When death appeared beside the Nazirite, his consecration was disrupted. In the same way, when the works of the flesh influence a believer, the visible glory of Messiah in that life becomes diminished.\nPrayer becomes weaker. Love of brethren grows cold. Words become harsh. The mind becomes restless. The walk loses its brightness. This does not mean Yahweh has abandoned His people, but it does show that consecration must be guarded carefully. The Nazirite’s defilement teaches us that even sudden exposure can interrupt devotion, and Yahweh calls us to respond quickly, not casually.\n\nSo, the call is to remain watchful and to keep walking in the Spirit, so that the life of Christ in us remains visible. Believers are called to live as new creations, separated to become like Christ. Just as the Nazirite’s consecration could be affected by death appearing beside him, we must be careful about what stays close to our life. We are not only to avoid the act of sin, but also the environment and influence that keep sin near. Yahweh’s wisdom is protective, not harsh.\nHe teaches us distance so that our vow is not quietly interrupted.\n\nWe will study tomorrow how and what all defile us and make us lose consecration."
  },
  {
    "type": "prayer",
    "title": "Prayer",
    "text": "Yahweh, the living God, keep our consecration clean and our hearts tender before You.\nTeach us to watch what stays close to our life, so that death does not disturb what is holy.\nGive us wisdom to separate from unfruitful works and courage to refuse corrupt influences.\nStrengthen our walk in purity, and keep Christ’s life visible in us.\nWhen we are exposed suddenly to sin around us, help us respond quickly with repentance and obedience.\nMay our vows not be interrupted, and may our devotion remain faithful to You.\nIn Christ, amen."
  }
]