[
  {
    "type": "meta",
    "title": "கோகாத்தியர்கள் – 8",
    "subtitle": "சமுகத்தப்ப மேஜை – 2",
    "language": "Tamil",
    "date": "2026-04-27",
    "youtubeUrl": "https://youtu.be/oEdjEhPAoF4",
    "pdfUrl": "https://themillenniumpost.com/download/morning-light/pdf/2026-APR-TA/27-04-2026-TA.pdf",
    "imageUrl": "",
    "audioUrl": ""
  },
  {
    "type": "verse",
    "reference": "எண்ணாகமம் அதிகாரம் 7:9",
    "text": "கோகாத்தின் புத்திரருக்கோ ஒன்றும் கொடுக்கவில்லை; தோள்மேல் சுமப்பதே அவர்களுக்குரிய பரிசுத்த ஸ்தலத்தின் வேலையாயிருந்தது."
  },
  {
    "type": "paragraph",
    "content": "நேற்று நாம் ஒரு கேள்வியைக் கேட்டோம், அதற்கு இப்போது நாம் பதிலளிக்க வேண்டும். நாம் சமுகத்தப்ப மேஜையைப் பார்த்தோம்; அதனுடைய மூன்று பெயர்கள், சீத்திம் மரம் மற்றும் தங்கத்தால் ஆன அதன் அமைப்பு, அதனுடைய தங்கக் கிரீடம், சுத்தமான தங்கத்தாலான அதன் பாத்திரங்கள், மற்றும் பரிசுத்த ஸ்தலத்தின் வடக்குச் சுவரில் உடன்படிக்கைப் பெட்டிக்கு நிகரான உயரத்தில் அது வைக்கப்பட்டிருந்த விதம் ஆகியவற்றை நாம் பார்த்தோம். ஆனால் நாம் அந்த மேஜையோடேயே நின்றுவிட்டோம், அதன் மீது என்ன இருந்தது என்பதைப் பற்றி நாம் இன்னும் பார்க்கவில்லை. இன்று நாம் அந்த அப்பத்தைப் பற்றி விரிவாகப் பார்க்கப் போகிறோம்; சமுகத்தப்பம் என்றால் என்ன, அது எப்படிச் செய்யப்பட்டது என்பதன் ஒவ்வொரு விவரத்தையும் ஆராய்ந்து, அதைச் சுட்டெடுத்த அந்தச் சிறப்பான குடும்பத்தைச் சந்தித்து, இறுதியாக, இன்று இந்த மேஜையைத் தங்கள் தோள்களில் சுமந்து செல்லும் சபைக்கு இதெல்லாம் என்ன அர்த்தத்தைக் கொடுக்கிறது என்பதைப் பார்த்து முடிக்கப் போகிறோம்.\n\nஇந்த அப்பத்திற்கான கட்டளைகள் லேவியராகமம் 24:5-9-ல் கொடுக்கப்பட்டுள்ளது. இந்த அப்பம் மிகச் சிறந்த தரமான கோதுமை மாவினால் செய்யப்பட்டது; இது சாதாரண மாவு அல்ல, மாறாகக் கிடைக்கக்கூடிய மிகச் சுத்தமான மற்றும் தூய்மையான மாவாகும்; ஒவ்வொரு கட்டியையும், ஒவ்வொரு அசுத்தத்தையும், ஒவ்வொரு சொரசொரப்பான தானியத்தையும் நீக்குவதற்காகப் பலமுறை சலிக்கப்பட்டு, மீதமிருப்பது மென்மையாகவும், சுத்தமாகவும், எந்தவித முரட்டுத்தன்மையும் இல்லாமல் இருக்கும் வரை அது தயார் செய்யப்பட்டது. இந்த மாவு மட்டுமே ஏற்றுக்கொள்ளப்பட்டது. தேவன் தமது மேஜையில் சாதாரண மாவை அனுமதிக்கவில்லை. மிகச் சிறந்ததே தேவைப்பட்டது, ஏனென்றால் அந்த மேஜை மிகச் சிறந்தவரின் முன்பாக நின்றது; சர்வ சிருஷ்டிக்கும் ராஜாவானவருடைய சமுகத்திற்கு முன்பாக நின்றது. பன்னிரண்டு அப்பங்களில் ஒவ்வொன்றிற்கும் பத்தில் இரண்டு எப்பா அளவிலான இந்த மெல்லிய மாவு தேவைப்பட்டது; அதாவது, ஒவ்வொரு அப்பத்திற்கும் தோராயமாக ஆறு பவுண்டு மாவு பயன்படுத்தப்பட்டது. இவை மெல்லிய அடைகளோ அல்லது சிறிய அடையாளத் துண்டுகளோ அல்ல. அவை கணிசமான, தாராளமான பெரிய அப்பங்களாக இருந்தது; உண்மையான எடையுடன், முழு அளவிற்கும் சுடப்பட்ட உண்மையான அப்பங்கள்.\n\nஒவ்வொரு அப்பமும் மற்றொன்றைப் போலவே சரியாகவும் ஒரே அளவிலும் இருந்தது. எந்தக் கோத்திரமும் மற்றொன்றை விடப் பெரிய அப்பத்தைப் பெறவில்லை. எந்தக் கோத்திரமும் சிறிய ஒன்றைப் பெறவில்லை. யாவே தேவனின் சமுகத்தில், பன்னிரண்டு கோத்திரங்களும் சமமாக நின்றது, அனைவருக்கும் சமமாக உணவளிக்கப்பட்டது, அனைவரும் சமமாகப் பிரதிநிதித்துவப்படுத்தப்பட்டனர். அந்தப் பன்னிரண்டு அப்பங்களும் மேஜையின் மீது ஆறு ஆறாக இரண்டு வரிசைகளில் அடுக்கப்பட்டிருந்தது; இரண்டு அடுக்குகள், மேஜையின் இடது பக்கத்தில் ஒன்றும் வலது பக்கத்தில் ஒன்றும் என, ஒவ்வொரு அடுக்கும் ஆறு அப்பங்கள் உயரத்தில் அடுக்கப்பட்டிருந்தது. எப்போதும் வரிசையாக. எப்போதும் முழுமையாக. எப்போதும் பன்னிரண்டாக. மேலும், ஒவ்வொரு அடுக்கின் மீதும் சுத்தமான தூபவர்க்கத்தால் நிரப்பப்பட்ட ஒரு தங்கக் கிண்ணம் வைக்கப்பட்டிருந்தது; அதனுடைய நறுமணம் அந்தப் பரிசுத்த அறையில் அமைதியாக எழும்பி, தேவனுக்கு முன்பாக ஏறிச் செல்லும் மக்களின் ஜெபங்களையும் ஆராதனையையும் குறிப்பதாக அமைந்தது.\n\nஒவ்வொரு ஓய்வுநாளிலும் தவறாமல், பழைய அப்பங்கள் மாற்றப்பட்டுப் புதிதாகச் சுடப்பட்ட அப்பங்கள் வைக்கப்பட்டது. பழைய அப்பங்கள் அகற்றப்படும்போது, ஆசாரியர்கள் புதிய அப்பங்களைக் கொண்டு வந்தார்கள். இந்த புதுப்பித்தல் இல்லாமல் ஒரு ஓய்வுநாள் கூடக் கடந்து சென்றதில்லை. பழைய அப்பங்கள் மேஜையிலிருந்து அகற்றப்பட்டபோது, அவை தூக்கி எறியப்படவோ அல்லது சாதாரண உணவாகக் கருதப்படவோ இல்லை. அவை ஆரோனாலும் அவனுடைய குமாரர்களாலும் பரிசுத்த ஸ்தலத்திற்குள்ளேயே உண்ணப்பட்டது; வெளியே கொண்டு செல்லப்படவில்லை, வீட்டில் உண்ணப்படவில்லை, பாளையத்தில் விநியோகிக்கப்படவும் இல்லை. அவை அந்தப் பரிசுத்த அறையிலேயே, தேவனுடைய சமுகத்தில் உட்கொள்ளப்பட வேண்டியதாக இருந்தது. இந்த அப்பம் மகா பரிசுத்தமானது என்று விவரிக்கப்பட்டது. அது மேஜையை விட்டு எடுக்கப்பட்ட பின்பும் கூடச் சாதாரணமான ஒரு பொருளாகக் கையாளப்படக் கூடாது.\n\nஇங்கே ஒரு விவரம் உள்ளது, இதைக் கடந்து செல்வது எளிது, ஆனால் அப்படிச் செய்துவிடக் கூடாது. 1 நாளாகமம் 9:32 மற்றும் 23:29 நமக்குச் சொல்வது என்னவென்றால், கோகாத்தியர்கள் சமுகத்தப்ப மேஜையை வனாந்தரத்தின் வழியே சுமந்து செல்வதற்கு மட்டும் பொறுப்பானவர்கள் அல்ல, ஒவ்வொரு வாரமும் அந்தச் சமுகத்தப்பத்தைச் சுடுவதற்கும், அதை வரிசையாக வைப்பதற்கும் அவர்களே பொறுப்பாக இருந்தார்கள். மேஜையைச் சுமந்த அதே மக்களே, அதன் மீது வைக்கப்பட்டிருந்ததையும் ஆயத்தம் செய்தார்கள். அவர்களின் பொறுப்பு வெறும் தூக்கிக்கொண்டு நடப்பது மட்டுமல்ல. மாவில் தொடங்கி, நெருப்பைக் கடந்து, அதைச் சுமந்து, தேவனுடைய சமுகத்திற்கு முன்பாக வைப்பது வரை அது நீண்டிருந்தது. அந்த மேஜையின் ஒவ்வொரு செயல்பாடும் கோகாத்தியர்களின் கைகளில்தான் இருந்தது.\n\nஎருசலேம் மற்றும் பாபிலோனிய தல்மூதில் குறிப்பிடப்பட்டுள்ளபடி, கோகாத்தியர்களில் கார்மு (Garmu) என்று அழைக்கப்பட்ட ஒரு குறிப்பிட்ட குடும்பம் இருந்தது; இதைப் பற்றி நாம் 1 நாளாகமம் 9:32-லும், \"அவர்கள் சகோதரராகிய கோகாத்தியரின் புத்திரரில் சிலருக்கு ஓய்வுநாள்தோறும் சமுகத்து அப்பங்களை ஆயத்தப்படுத்தும் விசாரிப்பு இருந்தது\" என்று வாசிக்கிறோம். சமுகத்தப்பத்தை எப்படிச் சரியாகச் சுடுவது என்ற ரகசிய அறிவை அவர்கள் கொண்டிருந்தார்கள். இந்த அப்பத்தைத் தயாரிப்பதற்குப் பரவலாக அறியப்படாத ஒரு குறிப்பிட்ட திறமை தேவைப்பட்டது, மேலும் கார்மு குடும்பம் அதை மிகவும் கவனமாகப் பாதுகாத்து வந்தது.\nஒருமுறை மக்கள் அந்த முறையை மற்றவர்களுக்குக் கற்றுக்கொடுக்குமாறு அவர்களிடம் கேட்டபோது, அவர்கள் மறுத்துவிட்டார்கள். அதற்கான காரணம் பெருமையோ அல்லது சுயநலமோ அல்ல. அது அவர்களின் பயபக்தி. அவர்கள் கூறினார்கள்: “ஒரு நாள் தேவாலயம் அழிக்கப்படும் என்று எங்களுக்குத் தெரியும், தகுதியற்ற ஒருவன் இந்த அப்பத்தை எப்படிச் சுடுவது என்பதைக் கற்றுக்கொண்டு, அந்த அறிவைப் பயன்படுத்தி ஒரு சிலைக்குச் சேவை செய்வதை நாங்கள் அனுமதிக்க மாட்டோம்.”\nதேவ சமுகத்தின் பரிசுத்த அப்பம் ஒரு பொய்த் தெய்வத்தின் சேவைக்காகப் பிரதிபலிக்கப்படுவதைப் பார்ப்பதை விட, தனிப்பட்ட முறையில் நஷ்டம் ஏற்பட்டாலும் கூட, அந்த ரகசியத்தைத் தங்களுக்குள்ளேயே வைத்திருக்கவே அவர்கள் விரும்பினார்கள். அவர்கள் அந்த அப்பத்தின் பரிசுத்தத்தைத் தங்கள் உயிரைக் கொடுத்துப் பாதுகாத்தார்கள்.\n\nகார்மு குடும்பத்திலிருந்த இந்த வைராக்கியம், தேவனுடைய காரியங்களைச் சுமக்கும் ஒவ்வொரு நபருக்குள்ளும் இருக்க வேண்டிய ஒன்றின் படமாக இருக்கிறது. அவர்கள் சமுகத்தப்பத்தைச் சாதாரண ஒரு பேக்கிங் வேலையாகக் கருதவில்லை. அதை ஒரு பரிசுத்தமான பொறுப்பாகவே நடத்தினார்கள். தேவனுடைய சமுகத்திற்கு முன்பாக வைக்கப்பட்ட ஒன்று, மலிவாகப் பிரதிபலிக்கப்படவோ அல்லது கவனக்குறைவாகத் தவறாகப் பயன்படுத்தப்படவோ கூடாது. கோகாத்தியர்கள் மேஜையைச் சுமந்தார்கள், அதன் மீதான அப்பத்தை ஆயத்தம் செய்தார்கள், மேலும் வேலையின் ஆரம்பம் முதல் முடிவு வரை இரண்டையும் மிகுந்த பயபக்தியோடு காத்தார்கள். தேவனுக்குச் சொந்தமானவற்றை நாம் சுமந்து செல்லும்போது, இன்றைக்குச் சபையை அடையாளப்படுத்த வேண்டிய ஆவி இதுதான்.\n\nஇப்போது நாம் சற்றுப் பின்வாங்கி முழுப் படத்தையும் பார்க்கலாம். சமுகத்தப்ப மேஜை என்பது வனாந்தரத்தின் நடுவே தேவனால் விரிக்கப்பட்ட ஒரு தங்க மேஜை. அதன் மீது மிகச் சிறந்த தரத்தாலான பன்னிரண்டு அப்பங்கள் சரியான வரிசையில் அடுக்கப்பட்டு, அவருடைய மக்கள் ஒவ்வொருவரையும் அவருடைய சமுகத்திற்கு முன்பாகப் பிரதிநிதித்துவப்படுத்தின. அது ஒருபோதும் காலியாக இருந்ததில்லை. அது ஒருபோதும் மறக்கப்படவில்லை. ஒவ்வொரு ஓய்வுநாளிலும் அது புதுப்பிக்கப்பட்டது. அது வனாந்தரப் பயணத்தின் வழியே கோகாத்தியர்களின் தோள்களில் சுமந்து செல்லப்பட்டது.\nஅது எப்போதும் யாவே தேவனின் சமுகத்திலேயே இருந்தது; உடன்படிக்கைப் பெட்டியின் அதே உயரத்தில் நின்றது, அப்பமும் மகிமையும் அருகருகே இருந்தது.\n\nபுதிய உடன்படிக்கையின் சபையாக நாம் இந்த மேஜையை நம் தோள்களில் சுமக்கும்போது, தேவன் தம் மக்களுக்கு உணவளிக்கிறார் என்ற சாட்சியை நாம் சுமக்கிறோம். எப்போதாவது அல்ல. சூழ்நிலைகள் சாதகமாக இருக்கும்போது அல்ல. தொடர்ச்சியாக. முழு வனாந்தரப் பயணத்திலும் அந்த மேஜை ஒருபோதும் காலியாகவே இருந்ததில்லை. அதைச் சுற்றியிருந்த வனாந்தரம் எவ்வளவு வறண்டதாக இருந்தாலும் சரி, பயணம் எவ்வளவு நீண்டதாகத் தோன்றினாலும் சரி, வாக்குத்தத்தம் பண்ணப்பட்ட தேசம் எவ்வளவு தூரத்தில் இருப்பதைப் போலத் தோன்றினாலும் சரி; அப்பம் எப்போதும் அங்கே இருந்தது. நாம் அந்தச் சாட்சியைத்தான் உலகத்திற்குள் சுமந்து செல்கிறோம். தேவனுடைய ஏற்பாடு ஒருபோதும் வறண்டு போகாது என்பதையும், அவருடைய மக்கள் ஒருபோதும் அவருடைய சமுகத்தை விட்டு விலகுவதில்லை என்பதையும், அவர்களில் ஒவ்வொருவரும்; பத்தும் அல்ல, பதினொன்றும் அல்ல, பன்னிரண்டும் முழுமையாக ராஜாவின் முன்பாக நினைவுகூரப்பட்டுப் பிரதிநிதித்துவப்படுத்தப்படுகிறார்கள் என்ற நற்செய்தியையும் நாம் சுமந்து செல்கிறோம்.\n\nநாம் ஒரு தனிப்பட்ட பொறுப்பையும் சுமக்கிறோம். கோகாத்தியர்கள் மேஜையைச் சுமப்பதற்கு முன்பாக அப்பத்தைச் சுட்டார்கள். தாங்கள் முதலில் ஆயத்தம் செய்யாத ஒன்றை அவர்களால் சுமக்க முடியாது. அதேபோல, நாம் முதலில் பெற்றுக்கொள்ளாத ஒன்றை மற்றவர்களிடம் கொண்டு செல்ல முடியாது. நாம் ஒருபோதும் சாப்பிடாத ஒரு அப்பத்தைக் கொண்டு பசியோடிருக்கும் உலகத்திற்கு நாம் உணவளிக்க முடியாது.\nசமுகத்தப்ப மேஜையைச் சுமக்கிற சபை முதலில் அந்த மேஜையில் உட்கார வேண்டும். முதலில் வார்த்தையை உட்கொள்ள வேண்டும். முதலில் தேவ பிரசன்னத்தைப் பெற்றுக்கொள்ள வேண்டும். ஊக்கமளிப்பத்தைச் சுமந்து செல்வதற்கு முன்பாக, முதலில் நாம் போஷிக்கப்பட வேண்டும். கார்மு குடும்பத்தினர், அந்த அப்பம் தேவனுக்கு முன்பாக வைக்கப்படுவதற்கு முன்னதாகவே, தங்கள் கைகளால் அதைச் சுட்டார்கள். புதிய சிருஷ்டியான கோகாத்தியர்கள், அவருடைய ஏற்பாட்டைப் பற்றிய சாட்சியை மற்ற எவரிடமும் கொண்டு செல்வதற்கு முன்பாக, முதலில் கிறிஸ்துவைத் தனிப்பட்ட முறையில் உட்கொள்ள வேண்டும்."
  },
  {
    "type": "prayer",
    "title": "ஜெபம்",
    "text": "யாவே தேவனே, நீர் என் மேய்ப்பராய் இருக்கிறீர், நான் தாழ்ச்சியடையேன் (சங்கீதம் 23:1). வனாந்தரத்தில் உமது மக்களுக்கு முன்பாக நீர் ஒரு பந்தியை ஆயத்தப்படுத்தினீர், ஒரு நாள் கூட அது காலியாக இருப்பதை நீர் அனுமதிக்கவில்லை. புதிய அப்பம் இல்லாமல் ஒரு ஓய்வுநாள் கூடக் கடந்து சென்றதில்லை. உமது மக்களின் சார்பாக உமது சமுகத்திற்கு முன்பாகத் தூபவர்க்கம் எழும்பாமல் ஒரு வாரம் கூடச் சென்றதில்லை.\nஎற்பாடு செய்கிற, நினைவுகூருகிற, மேஜையின் மீதுள்ள பன்னிரண்டு அப்பங்களையும் பத்திரமாக வைத்து எதையும் விட்டுவிடாத தேவனாக நீர் இருப்பதற்காக உமக்கு நன்றி செலுத்துகிறோம். அந்த மேஜையில் முதலில் அமராமல், அதைச் சுமந்து செல்ல நாங்கள் முயற்சித்த நேரங்களுக்காக எங்களை மன்னியுங்கள்; நாங்கள் உண்ணாத அப்பத்தைக் கொண்டு மற்றவர்களுக்கு உணவளிக்க முயன்றதற்காவும், நாங்கள் பெற்றுக்கொள்ளாத போஷாக்கை மற்றவர்களுக்குக் கொடுக்க முயன்றதற்காவும் எங்களை மன்னியுங்கள். உம்மை எங்குச் சுமந்து செல்வதற்கு முன்பாகவும், ஒவ்வொரு காலையிலும், முதலில் உம்மை உட்கொள்ள எங்களுக்குக் கற்றும் தாருங்கள். அதன்பின்பு, சமுகத்தப்ப மேஜையை எங்கள் தோள்களில் சுமந்துகொண்டு எங்களை வெளியே அனுப்புங்கள்; உமது ஏற்பாடு உண்மையானது, உமது மக்கள் உமது சமுகத்திற்கு முன்பாக இருக்கிறார்கள், உமது மேஜை ஒருபோதும் வெறுமையாக இருப்பதில்லை என்ற சாட்சியைச் சுமந்துகொண்டு செல்லும்படி செய்யுங்கள். தேவனுடைய சமுகத்தில் அப்பம் இருக்கிறது என்பதையும், அதுவே போதுமானது என்பதையும் உலகம் எங்கள் மூலமாகப் பார்க்கட்டும்.\n\nகிறிஸ்துவின் நாமத்தில் பிதாவே, ஆமென்."
  }
]